setup.py
jinjastatic/__init__.py
jinjastatic/dependencies.py
jinjastatic/jinjatagext.py
jinjastatic/staticlib.py
jinjastatic/utils.py
jinjastatic/watcher.py
jinjastatic.egg-info/PKG-INFO
jinjastatic.egg-info/SOURCES.txt
jinjastatic.egg-info/dependency_links.txt
jinjastatic.egg-info/entry_points.txt
jinjastatic.egg-info/not-zip-safe
jinjastatic.egg-info/requires.txt
jinjastatic.egg-info/top_level.txt