Metadata-Version: 1.0
Name: jinjastatic
Version: 0.0.7
Summary: Static template compilation
Home-page: UNKNOWN
Author: Michael Axiak
Author-email: mike@axiak.net
License: MIT
Platform: UNKNOWN
Classifier: Development Status :: 4 - Beta
Classifier: Environment :: Other Environment
Classifier: Intended Audience :: Developers
Classifier: License :: OSI Approved :: MIT License
Classifier: Topic :: Software Development :: Libraries :: Python Modules
Classifier: Topic :: Internet :: WWW/HTTP
Classifier: Topic :: Internet :: WWW/HTTP :: Dynamic Content
